Metadata-Version: 1.2
Name: world-time
Version: 0.0.3
Summary: Be in time
Home-page: UNKNOWN
Author: SDA
Author-email: sda@sda.pl
License: UNKNOWN
Platform: UNKNOWN
Requires-Python: >=3.6
